{
  "scan_time": "2026-06-30 22:13:14",
  "scanner_version": "v4.0",
  "source_stats": {
    "엔터 많이 본 뉴스": 30,
    "엔터 5분 랭킹": 0,
    "스포츠 많이 본 뉴스": 20,
    "스포츠 5분 랭킹": 0,
    "DC 연예인 갤러리": 0,
    "DC 국내야구 갤러리": 0,
    "MLB파크 불펜": 30
  },
  "total_articles": 80,
  "articles": [
    {
      "title": "\"코치 연봉 5천, 월급은 10개월만\"…임창용이 토로한, 레전드들이 현장에 없는 이유 \"처우 개선 시급\"",
      "url": "",
      "source": "스포츠 많이 본 뉴스",
      "category": "스포츠",
      "views": 152942,
      "rank": 8,
      "channel": "초구딱"
    },
    {
      "title": "충격 시나리오, 이정후 디트로이트行 \"타선에 안정감 더해줄 것\" 美 매체 파격 주장...SF에 트레이드 제안하나",
      "url": "",
      "source": "스포츠 많이 본 뉴스",
      "category": "스포츠",
      "views": 123236,
      "rank": 11,
      "channel": "초구딱"
    },
    {
      "title": "'이범호 뚝심 대단하네' 갈 길 바쁜 KIA, 오늘(30일) 'ERA 1위' 에이스 투구 후 휴식 준다…\"1승보다 중요한 게 있다\"",
      "url": "",
      "source": "스포츠 많이 본 뉴스",
      "category": "스포츠",
      "views": 96999,
      "rank": 15,
      "channel": "초구딱"
    },
    {
      "title": "“홍명보 감독 월드컵 성공했어도 사퇴 고려”…12년 전 상처 더 벌어졌다, 끝내 자진해서 아웃",
      "url": "",
      "source": "스포츠 많이 본 뉴스",
      "category": "스포츠",
      "views": 96672,
      "rank": 16,
      "channel": "초구딱"
    },
    {
      "title": "\"정말 죄송합니다\" 브라질에 지고 눈물로 사과한 日감독, 홍명보는 귀국길조차 '침묵'",
      "url": "",
      "source": "스포츠 많이 본 뉴스",
      "category": "스포츠",
      "views": 80180,
      "rank": 19,
      "channel": "초구딱"
    },
    {
      "title": "'물 한병이라도 좋으니 제발 도와주세요' 한화 외인, 조국 덮친 참사에 도움 호소…결승포보다 간절했던 부탁",
      "url": "",
      "source": "스포츠 많이 본 뉴스",
      "category": "스포츠",
      "views": 78766,
      "rank": 20,
      "channel": "초구딱"
    },
    {
      "title": "정치 말머리 위반 처리 및 향후 진행 예정 사항 (23.06.19 시행)",
      "url": "https://mlbpark.donga.com/mp/b.php?p=1&b=notice&id=202306190000001281",
      "source": "MLB파크 불펜",
      "category": "야구",
      "views": 0,
      "rank": 1,
      "channel": "초구딱"
    },
    {
      "title": "🛠️[공지] 해외 접속 장애 관련 안내_260522🛠️",
      "url": "https://mlbpark.donga.com/mp/b.php?b=notice&id=202605220000002082",
      "source": "MLB파크 불펜",
      "category": "야구",
      "views": 0,
      "rank": 2,
      "channel": "초구딱"
    },
    {
      "title": "⚽[공지] 월드컵 기간 내 전용 게시판 운영 예정 안내⚽",
      "url": "https://mlbpark.donga.com/mp/b.php?p=1&b=notice&id=202606080000002102",
      "source": "MLB파크 불펜",
      "category": "야구",
      "views": 0,
      "rank": 3,
      "channel": "초구딱"
    },
    {
      "title": "🏆[6/30 Update!] 2026 북중미월드컵 승부예측 이벤트🏆",
      "url": "https://mlbpark.donga.com/mp/b.php?p=1&b=worldcup&id=202606100116098223",
      "source": "MLB파크 불펜",
      "category": "야구",
      "views": 0,
      "rank": 4,
      "channel": "초구딱"
    },
    {
      "title": "🏆7/1(수) 2026 WC 승부예측 바로가기 [32강]🏆",
      "url": "https://mlbpark.donga.com/mp/b.php?p=1&b=worldcup&id=202606290116776598",
      "source": "MLB파크 불펜",
      "category": "야구",
      "views": 0,
      "rank": 5,
      "channel": "초구딱"
    },
    {
      "title": "🏆7/2(목) 2026 WC 승부예측 바로가기 [32강]🏆",
      "url": "https://mlbpark.donga.com/mp/b.php?p=1&b=worldcup&id=202606290116776622",
      "source": "MLB파크 불펜",
      "category": "야구",
      "views": 0,
      "rank": 6,
      "channel": "초구딱"
    },
    {
      "title": "🏆7/3(금) 2026 WC 승부예측 바로가기 [32강]🏆",
      "url": "https://mlbpark.donga.com/mp/b.php?p=1&b=worldcup&id=202606290116776628",
      "source": "MLB파크 불펜",
      "category": "야구",
      "views": 0,
      "rank": 7,
      "channel": "초구딱"
    },
    {
      "title": "프랑스는 체급이 다르네요",
      "url": "https://mlbpark.donga.com/mp/b.php?id=202607010116835617&p=1&b=bullpen&m=view&select=&query=&subselect=&subquery=&user=&site=donga.com",
      "source": "MLB파크 불펜",
      "category": "야구",
      "views": 0,
      "rank": 8,
      "channel": "초구딱"
    },
    {
      "title": "프랑스는 어나더레벨인요",
      "url": "https://mlbpark.donga.com/mp/b.php?id=202607010116835614&p=1&b=bullpen&m=view&select=&query=&subselect=&subquery=&user=&site=donga.com",
      "source": "MLB파크 불펜",
      "category": "야구",
      "views": 22,
      "rank": 9,
      "channel": "초구딱"
    },
    {
      "title": "올리세 진짜 겁나게 잘하네요 ㄷㄷㄷㄷ",
      "url": "https://mlbpark.donga.com/mp/b.php?id=202607010116835611&p=1&b=bullpen&m=view&select=&query=&subselect=&subquery=&user=&site=donga.com",
      "source": "MLB파크 불펜",
      "category": "야구",
      "views": 16,
      "rank": 10,
      "channel": "초구딱"
    },
    {
      "title": "코트디부아르도 월드컵 성적 은근히 구리더군요",
      "url": "https://mlbpark.donga.com/mp/b.php?id=202607010116835608&p=1&b=bullpen&m=view&select=&query=&subselect=&subquery=&user=&site=donga.com",
      "source": "MLB파크 불펜",
      "category": "야구",
      "views": 14,
      "rank": 11,
      "channel": "초구딱"
    },
    {
      "title": "곽승석 은퇴",
      "url": "https://mlbpark.donga.com/mp/b.php?id=202607010116835605&p=1&b=bullpen&m=view&select=&query=&subselect=&subquery=&user=&site=donga.com",
      "source": "MLB파크 불펜",
      "category": "야구",
      "views": 20,
      "rank": 12,
      "channel": "초구딱"
    },
    {
      "title": "프랑스 2:0",
      "url": "https://mlbpark.donga.com/mp/b.php?id=202607010116835602&p=1&b=bullpen&m=view&select=&query=&subselect=&subquery=&user=&site=donga.com",
      "source": "MLB파크 불펜",
      "category": "야구",
      "views": 29,
      "rank": 13,
      "channel": "초구딱"
    },
    {
      "title": "올리세가 다 만들었네요 ㅋ",
      "url": "https://mlbpark.donga.com/mp/b.php?id=202607010116835596&p=1&b=bullpen&m=view&select=&query=&subselect=&subquery=&user=&site=donga.com",
      "source": "MLB파크 불펜",
      "category": "야구",
      "views": 91,
      "rank": 14,
      "channel": "초구딱"
    },
    {
      "title": "역시 프랑스가 ㅈ바르네 ㄷㄷㄷㄷ",
      "url": "https://mlbpark.donga.com/mp/b.php?id=202607010116835593&p=1&b=bullpen&m=view&select=&query=&subselect=&subquery=&user=&site=donga.com",
      "source": "MLB파크 불펜",
      "category": "야구",
      "views": 40,
      "rank": 15,
      "channel": "초구딱"
    },
    {
      "title": "프랑스 보면 아프리카가 경제대국 이였으면 축구 노잼이였을듯",
      "url": "https://mlbpark.donga.com/mp/b.php?id=202607010116835590&p=1&b=bullpen&m=view&select=&query=&subselect=&subquery=&user=&site=donga.com",
      "source": "MLB파크 불펜",
      "category": "야구",
      "views": 26,
      "rank": 16,
      "channel": "초구딱"
    },
    {
      "title": "???:코트디부아르 고개를 들어라.jpg",
      "url": "https://mlbpark.donga.com/mp/b.php?id=202607010116835587&p=1&b=bullpen&m=view&select=&query=&subselect=&subquery=&user=&site=donga.com",
      "source": "MLB파크 불펜",
      "category": "야구",
      "views": 100,
      "rank": 17,
      "channel": "초구딱"
    },
    {
      "title": "마이클 잭슨 내한공연 당시 잭슨에게 안긴 팬들",
      "url": "https://mlbpark.donga.com/mp/b.php?id=202607010116835578&p=1&b=bullpen&m=view&select=&query=&subselect=&subquery=&user=&site=donga.com",
      "source": "MLB파크 불펜",
      "category": "야구",
      "views": 55,
      "rank": 18,
      "channel": "초구딱"
    },
    {
      "title": "다른나라 유니폼은 저리 이쁘게 만들면서",
      "url": "https://mlbpark.donga.com/mp/b.php?id=202607010116835575&p=1&b=bullpen&m=view&select=&query=&subselect=&subquery=&user=&site=donga.com",
      "source": "MLB파크 불펜",
      "category": "야구",
      "views": 94,
      "rank": 19,
      "channel": "초구딱"
    },
    {
      "title": "제가 배재고에서 수능봤었는데 ㅋㅋ",
      "url": "https://mlbpark.donga.com/mp/b.php?id=202607010116835572&p=1&b=bullpen&m=view&select=&query=&subselect=&subquery=&user=&site=donga.com",
      "source": "MLB파크 불펜",
      "category": "야구",
      "views": 91,
      "rank": 20,
      "channel": "초구딱"
    },
    {
      "title": "그냥 앞으로 월드컵은 미국에서 하면 좋겠네요 ㅎㅎ",
      "url": "https://mlbpark.donga.com/mp/b.php?id=202607010116835569&p=1&b=bullpen&m=view&select=&query=&subselect=&subquery=&user=&site=donga.com",
      "source": "MLB파크 불펜",
      "category": "야구",
      "views": 142,
      "rank": 21,
      "channel": "초구딱"
    },
    {
      "title": "어제 비닐신.오늘 음바페",
      "url": "https://mlbpark.donga.com/mp/b.php?id=202607010116835563&p=1&b=bullpen&m=view&select=&query=&subselect=&subquery=&user=&site=donga.com",
      "source": "MLB파크 불펜",
      "category": "야구",
      "views": 91,
      "rank": 22,
      "channel": "초구딱"
    },
    {
      "title": "음바페가 앙레벤수 넘었나요?",
      "url": "https://mlbpark.donga.com/mp/b.php?id=202607010116835557&p=1&b=bullpen&m=view&select=&query=&subselect=&subquery=&user=&site=donga.com",
      "source": "MLB파크 불펜",
      "category": "야구",
      "views": 118,
      "rank": 23,
      "channel": "초구딱"
    },
    {
      "title": "프랑스 상대로는 라인 못올리겠네요",
      "url": "https://mlbpark.donga.com/mp/b.php?id=202607010116835554&p=1&b=bullpen&m=view&select=&query=&subselect=&subquery=&user=&site=donga.com",
      "source": "MLB파크 불펜",
      "category": "야구",
      "views": 79,
      "rank": 24,
      "channel": "초구딱"
    },
    {
      "title": "홀란드 결승골 순간 노르웨이 현지",
      "url": "https://mlbpark.donga.com/mp/b.php?id=202607010116835551&p=1&b=bullpen&m=view&select=&query=&subselect=&subquery=&user=&site=donga.com",
      "source": "MLB파크 불펜",
      "category": "야구",
      "views": 715,
      "rank": 25,
      "channel": "초구딱"
    },
    {
      "title": "일본이랑 프랑스랑 붙었으면 누가 이겼을까요?",
      "url": "https://mlbpark.donga.com/mp/b.php?id=202607010116835548&p=1&b=bullpen&m=view&select=&query=&subselect=&subquery=&user=&site=donga.com",
      "source": "MLB파크 불펜",
      "category": "야구",
      "views": 130,
      "rank": 26,
      "channel": "초구딱"
    },
    {
      "title": "[아이즈원] 김민주",
      "url": "https://mlbpark.donga.com/mp/b.php?id=202607010116835545&p=1&b=bullpen&m=view&select=&query=&subselect=&subquery=&user=&site=donga.com",
      "source": "MLB파크 불펜",
      "category": "야구",
      "views": 89,
      "rank": 27,
      "channel": "초구딱"
    },
    {
      "title": "올리세는 소속팀이 어디죠?",
      "url": "https://mlbpark.donga.com/mp/b.php?id=202607010116835539&p=1&b=bullpen&m=view&select=&query=&subselect=&subquery=&user=&site=donga.com",
      "source": "MLB파크 불펜",
      "category": "야구",
      "views": 301,
      "rank": 28,
      "channel": "초구딱"
    },
    {
      "title": "이 가족 서로 화해가 가능하다고 생각하세요?",
      "url": "https://mlbpark.donga.com/mp/b.php?id=202607010116835536&p=1&b=bullpen&m=view&select=&query=&subselect=&subquery=&user=&site=donga.com",
      "source": "MLB파크 불펜",
      "category": "야구",
      "views": 238,
      "rank": 29,
      "channel": "초구딱"
    },
    {
      "title": "음바페 와서 레알 챔스나 리그 우승할줄 알았더니",
      "url": "https://mlbpark.donga.com/mp/b.php?id=202607010116835533&p=1&b=bullpen&m=view&select=&query=&subselect=&subquery=&user=&site=donga.com",
      "source": "MLB파크 불펜",
      "category": "야구",
      "views": 118,
      "rank": 30,
      "channel": "초구딱"
    }
  ],
  "channels": {
    "정보주는하마": {
      "article_count": 44,
      "topics": [
        {
          "title": "\"월드컵\" 관련 화제 스타 TOP10",
          "angle_type": "👤 월드컵",
          "article_count": 6,
          "source_article": "어디 홍명보가 끝일쏘냐!..\"2030년 월드컵, 정중히 부탁\" 손흥민 사과에 김희철 등 ★들 들썩",
          "source_url": "https://m.entertain.naver.com/article/108/0003448771",
          "source_name": "엔터 많이 본 뉴스",
          "related_names": [
            "월드컵"
          ],
          "template": "인맥",
          "score": 7.4,
          "dup_check": {
            "is_duplicate": false,
            "status": "통과",
            "matched_title": "",
            "matched_views": 0,
            "reason": ""
          },
          "table": {
            "headers": [
              "이름",
              "분류",
              "이슈 내용",
              "현재 상황"
            ]
          },
          "channel": "정보주는하마"
        },
        {
          "title": "\"이 둘이 가족이라고?\" 놀라운 연예계 혈연 TOP10",
          "angle_type": "가족·혈연",
          "article_count": 3,
          "source_article": "\"5분 대기조처럼...\" 이혼 최동석, 손주 시중드는 부모님 보며 '씁쓸·뭉클'",
          "source_url": "https://m.entertain.naver.com/article/076/0004420761",
          "source_name": "엔터 많이 본 뉴스",
          "related_names": [
            "대기조",
            "이혼",
            "최동석",
            "손주",
            "시중드"
          ],
          "template": "동갑내기",
          "score": 6.9,
          "dup_check": {
            "is_duplicate": false,
            "status": "통과",
            "matched_title": "",
            "matched_views": 0,
            "reason": ""
          },
          "table": {
            "headers": [
              "이름",
              "나이",
              "대표작",
              "현재 활동"
            ]
          },
          "channel": "정보주는하마"
        },
        {
          "title": "\"임신 결혼 상대가 누구?\" 화제의 결혼 발표 스타 TOP10",
          "angle_type": "결혼·이혼",
          "article_count": 9,
          "source_article": "배우♥아나운서 부부 탄생...'혼전 임신' 발표→\"새로운 생명 찾아왔다\"",
          "source_url": "https://m.entertain.naver.com/article/445/0000432524",
          "source_name": "엔터 많이 본 뉴스",
          "related_names": [
            "임신",
            "결혼",
            "부부",
            "생명",
            "열애"
          ],
          "template": "결혼 화제",
          "score": 6.8,
          "dup_check": {
            "is_duplicate": false,
            "status": "통과",
            "matched_title": "",
            "matched_views": 0,
            "reason": ""
          },
          "table": {
            "headers": [
              "이름",
              "배우자",
              "결혼 시점",
              "화제 포인트"
            ]
          },
          "channel": "정보주는하마"
        },
        {
          "title": "\"홍명보, 역대급 기록?\" 스포츠 레전드 기록 TOP10",
          "angle_type": "스포츠",
          "article_count": 4,
          "source_article": "“이재명 대통령이 문체부에 조사 지시하자, 홍명보 감독이 즉각 사임해” 글로벌 스포츠 전문 매체 디 애슬레틱, 韓 축구 집중 조명",
          "source_url": "",
          "source_name": "스포츠 많이 본 뉴스",
          "related_names": [
            "홍명보",
            "이재명",
            "문체부",
            "조사",
            "지시하"
          ],
          "template": "스포츠 기록",
          "score": 6.8,
          "dup_check": {
            "is_duplicate": false,
            "status": "통과",
            "matched_title": "",
            "matched_views": 0,
            "reason": ""
          },
          "table": {
            "headers": [
              "선수",
              "소속팀",
              "기록 내용",
              "기록 가치"
            ]
          },
          "channel": "정보주는하마"
        },
        {
          "title": "\"배재고까지 이럴 줄은...\" 올해 팬들 분노 터진 스타 TOP10",
          "angle_type": "논란·사건",
          "article_count": 3,
          "source_article": "JK김동욱, ‘5·18 조롱구호 논란’ 배재고 교육청 조사에 “제대로 긁혔구나”",
          "source_url": "https://m.entertain.naver.com/article/144/0001123554",
          "source_name": "엔터 많이 본 뉴스",
          "related_names": [
            "배재고",
            "스타벅",
            "가야지",
            "김동욱",
            "조롱구"
          ],
          "template": "논란 집합",
          "score": 6.5,
          "dup_check": {
            "is_duplicate": false,
            "status": "통과",
            "matched_title": "",
            "matched_views": 0,
            "reason": ""
          },
          "table": {
            "headers": [
              "이름",
              "소속·직업",
              "논란 내용",
              "현재 상황"
            ]
          },
          "channel": "정보주는하마"
        },
        {
          "title": "\"축구\" 관련 화제 스타 TOP10",
          "angle_type": "👤 축구",
          "article_count": 4,
          "source_article": "홍명보 사퇴하고 6시간 뒤…'한국행 결렬' 마치는 캐나다 축구 영웅 됐다→\"역사적인 질주\" 英 BBC 등 외신도 극찬",
          "source_url": "",
          "source_name": "스포츠 많이 본 뉴스",
          "related_names": [
            "축구"
          ],
          "template": "인맥",
          "score": 6.5,
          "dup_check": {
            "is_duplicate": false,
            "status": "재활용 가능",
            "matched_title": "\"임영웅, 손흥민이랑 조기축구?\" 축구 좀 찬다고 알려진 스타 TOP10 #연예인 #스포츠 #축구",
            "matched_views": 32359,
            "reason": "기간 경과 104일"
          },
          "table": {
            "headers": [
              "이름",
              "분류",
              "이슈 내용",
              "현재 상황"
            ]
          },
          "channel": "정보주는하마"
        },
        {
          "title": "\"극찬\" 관련 화제 스타 TOP10",
          "angle_type": "👤 극찬",
          "article_count": 3,
          "source_article": "성시경, 문가영 극찬…\"너무 예쁘고 고급스러워\"",
          "source_url": "https://m.entertain.naver.com/article/003/0014035457",
          "source_name": "엔터 많이 본 뉴스",
          "related_names": [
            "극찬"
          ],
          "template": "인맥",
          "score": 6.0,
          "dup_check": {
            "is_duplicate": false,
            "status": "통과",
            "matched_title": "",
            "matched_views": 0,
            "reason": ""
          },
          "table": {
            "headers": [
              "이름",
              "분류",
              "이슈 내용",
              "현재 상황"
            ]
          },
          "channel": "정보주는하마"
        },
        {
          "title": "\"매체\" 관련 화제 스타 TOP10",
          "angle_type": "👤 매체",
          "article_count": 3,
          "source_article": "'벤투, 흥미로운 제안 기다리고 있다'…공백기 조명한 포르투갈 매체→韓 팬들은 '제발 돌아와 주세요'",
          "source_url": "",
          "source_name": "스포츠 많이 본 뉴스",
          "related_names": [
            "매체"
          ],
          "template": "인맥",
          "score": 6.0,
          "dup_check": {
            "is_duplicate": false,
            "status": "통과",
            "matched_title": "",
            "matched_views": 0,
            "reason": ""
          },
          "table": {
            "headers": [
              "이름",
              "분류",
              "이슈 내용",
              "현재 상황"
            ]
          },
          "channel": "정보주는하마"
        },
        {
          "title": "\"그때 그 사람, 지금은?\" 근황 궁금한 스타 TOP10",
          "angle_type": "복귀·근황",
          "article_count": 2,
          "source_article": "'벤투, 흥미로운 제안 기다리고 있다'…공백기 조명한 포르투갈 매체→韓 팬들은 '제발 돌아와 주세요'",
          "source_url": "",
          "source_name": "스포츠 많이 본 뉴스",
          "related_names": [
            "스타강",
            "김미경",
            "빼고",
            "얼굴",
            "몰라볼"
          ],
          "template": "장기 공백 복귀",
          "score": 5.8,
          "dup_check": {
            "is_duplicate": false,
            "status": "통과",
            "matched_title": "",
            "matched_views": 0,
            "reason": ""
          },
          "table": {
            "headers": [
              "이름",
              "공백 기간",
              "공백 사유",
              "복귀 작품"
            ]
          },
          "channel": "정보주는하마"
        },
        {
          "title": "\"죽을 고비 넘기고 돌아왔다\" 투병 이겨낸 스타 TOP10",
          "angle_type": "투병·건강",
          "article_count": 2,
          "source_article": "\"사망 이틀 전 찜질방 같이 갔는데\" 故 강수연, 향년 56세→동료 여배우 '그리움' 호소 ('당신이아픈사이')",
          "source_url": "https://m.entertain.naver.com/article/445/0000432558",
          "source_name": "엔터 많이 본 뉴스",
          "related_names": [
            "사망",
            "이틀",
            "찜질방",
            "같이",
            "갔는데"
          ],
          "template": "투병 극복",
          "score": 5.5,
          "dup_check": {
            "is_duplicate": false,
            "status": "통과",
            "matched_title": "",
            "matched_views": 0,
            "reason": ""
          },
          "table": {
            "headers": [
              "이름",
              "투병 질환",
              "공백기",
              "복귀 작품"
            ]
          },
          "channel": "정보주는하마"
        }
      ],
      "keyword_freq": [
        [
          "월드컵",
          4
        ],
        [
          "배재고",
          4
        ],
        [
          "축구",
          4
        ],
        [
          "임신",
          3
        ],
        [
          "결혼",
          3
        ],
        [
          "극찬",
          3
        ],
        [
          "홍명보",
          3
        ],
        [
          "매체",
          3
        ],
        [
          "부부",
          2
        ],
        [
          "생명",
          2
        ],
        [
          "인정",
          2
        ],
        [
          "열애",
          2
        ],
        [
          "사망",
          2
        ],
        [
          "내가",
          2
        ],
        [
          "깜짝",
          2
        ],
        [
          "이제",
          2
        ],
        [
          "얼굴",
          2
        ],
        [
          "불꽃야구",
          2
        ],
        [
          "위로",
          2
        ],
        [
          "가야지",
          2
        ]
      ],
      "name_freq": [
        [
          "홍명보",
          6
        ],
        [
          "월드컵",
          6
        ],
        [
          "배재고",
          4
        ],
        [
          "축구",
          4
        ],
        [
          "임신",
          3
        ],
        [
          "결혼",
          3
        ],
        [
          "극찬",
          3
        ],
        [
          "매체",
          3
        ],
        [
          "생명",
          2
        ],
        [
          "부부",
          2
        ],
        [
          "인정",
          2
        ],
        [
          "열애",
          2
        ],
        [
          "사망",
          2
        ],
        [
          "내가",
          2
        ],
        [
          "깜짝",
          2
        ]
      ],
      "angle_scores": [
        [
          "논란·사건",
          3
        ],
        [
          "결혼·이혼",
          9
        ],
        [
          "복귀·근황",
          2
        ],
        [
          "투병·건강",
          2
        ],
        [
          "스포츠",
          4
        ],
        [
          "가족·혈연",
          3
        ]
      ]
    },
    "초구딱": {
      "article_count": 36,
      "topics": [
        {
          "title": "\"홍명보, 역대급 기록?\" 스포츠 레전드 기록 TOP10",
          "angle_type": "스포츠",
          "article_count": 6,
          "source_article": "\"코치 연봉 5천, 월급은 10개월만\"…임창용이 토로한, 레전드들이 현장에 없는 이유 \"처우 개선 시급\"",
          "source_url": "",
          "source_name": "스포츠 많이 본 뉴스",
          "related_names": [
            "홍명보",
            "감독",
            "코치",
            "연봉",
            "월급은"
          ],
          "template": "스포츠 기록",
          "score": 7.3,
          "dup_check": {
            "is_duplicate": false,
            "status": "통과",
            "matched_title": "",
            "matched_views": 0,
            "reason": ""
          },
          "table": {
            "headers": [
              "선수",
              "소속팀",
              "기록 내용",
              "기록 가치"
            ]
          },
          "channel": "초구딱"
        },
        {
          "title": "\"월드컵\" 관련 화제 스타 TOP10",
          "angle_type": "👤 월드컵",
          "article_count": 5,
          "source_article": "“홍명보 감독 월드컵 성공했어도 사퇴 고려”…12년 전 상처 더 벌어졌다, 끝내 자진해서 아웃",
          "source_url": "",
          "source_name": "스포츠 많이 본 뉴스",
          "related_names": [
            "월드컵"
          ],
          "template": "인맥",
          "score": 7.0,
          "dup_check": {
            "is_duplicate": false,
            "status": "통과",
            "matched_title": "",
            "matched_views": 0,
            "reason": ""
          },
          "table": {
            "headers": [
              "이름",
              "분류",
              "이슈 내용",
              "현재 상황"
            ]
          },
          "channel": "초구딱"
        },
        {
          "title": "\"프랑스\" 관련 화제 스타 TOP10",
          "angle_type": "👤 프랑스",
          "article_count": 7,
          "source_article": "프랑스는 체급이 다르네요",
          "source_url": "https://mlbpark.donga.com/mp/b.php?id=202607010116835617&p=1&b=bullpen&m=view&select=&query=&subselect=&subquery=&user=&site=donga.com",
          "source_name": "MLB파크 불펜",
          "related_names": [
            "프랑스"
          ],
          "template": "인맥",
          "score": 6.5,
          "dup_check": {
            "is_duplicate": false,
            "status": "통과",
            "matched_title": "",
            "matched_views": 0,
            "reason": ""
          },
          "table": {
            "headers": [
              "이름",
              "분류",
              "이슈 내용",
              "현재 상황"
            ]
          },
          "channel": "초구딱"
        },
        {
          "title": "\"승부예\" 관련 화제 스타 TOP10",
          "angle_type": "👤 승부예",
          "article_count": 4,
          "source_article": "🏆[6/30 Update!] 2026 북중미월드컵 승부예측 이벤트🏆",
          "source_url": "https://mlbpark.donga.com/mp/b.php?p=1&b=worldcup&id=202606100116098223",
          "source_name": "MLB파크 불펜",
          "related_names": [
            "승부예"
          ],
          "template": "인맥",
          "score": 6.5,
          "dup_check": {
            "is_duplicate": false,
            "status": "통과",
            "matched_title": "",
            "matched_views": 0,
            "reason": ""
          },
          "table": {
            "headers": [
              "이름",
              "분류",
              "이슈 내용",
              "현재 상황"
            ]
          },
          "channel": "초구딱"
        },
        {
          "title": "\"바로가\" 관련 화제 스타 TOP10",
          "angle_type": "👤 바로가",
          "article_count": 3,
          "source_article": "🏆7/1(수) 2026 WC 승부예측 바로가기 [32강]🏆",
          "source_url": "https://mlbpark.donga.com/mp/b.php?p=1&b=worldcup&id=202606290116776598",
          "source_name": "MLB파크 불펜",
          "related_names": [
            "바로가"
          ],
          "template": "인맥",
          "score": 6.0,
          "dup_check": {
            "is_duplicate": false,
            "status": "통과",
            "matched_title": "",
            "matched_views": 0,
            "reason": ""
          },
          "table": {
            "headers": [
              "이름",
              "분류",
              "이슈 내용",
              "현재 상황"
            ]
          },
          "channel": "초구딱"
        },
        {
          "title": "\"올리세\" 관련 화제 스타 TOP10",
          "angle_type": "👤 올리세",
          "article_count": 3,
          "source_article": "올리세 진짜 겁나게 잘하네요 ㄷㄷㄷㄷ",
          "source_url": "https://mlbpark.donga.com/mp/b.php?id=202607010116835611&p=1&b=bullpen&m=view&select=&query=&subselect=&subquery=&user=&site=donga.com",
          "source_name": "MLB파크 불펜",
          "related_names": [
            "올리세"
          ],
          "template": "인맥",
          "score": 6.0,
          "dup_check": {
            "is_duplicate": false,
            "status": "통과",
            "matched_title": "",
            "matched_views": 0,
            "reason": ""
          },
          "table": {
            "headers": [
              "이름",
              "분류",
              "이슈 내용",
              "현재 상황"
            ]
          },
          "channel": "초구딱"
        },
        {
          "title": "\"음바페\" 관련 화제 스타 TOP10",
          "angle_type": "👤 음바페",
          "article_count": 3,
          "source_article": "어제 비닐신.오늘 음바페",
          "source_url": "https://mlbpark.donga.com/mp/b.php?id=202607010116835563&p=1&b=bullpen&m=view&select=&query=&subselect=&subquery=&user=&site=donga.com",
          "source_name": "MLB파크 불펜",
          "related_names": [
            "음바페"
          ],
          "template": "인맥",
          "score": 6.0,
          "dup_check": {
            "is_duplicate": false,
            "status": "통과",
            "matched_title": "",
            "matched_views": 0,
            "reason": ""
          },
          "table": {
            "headers": [
              "이름",
              "분류",
              "이슈 내용",
              "현재 상황"
            ]
          },
          "channel": "초구딱"
        }
      ],
      "keyword_freq": [
        [
          "승부예측",
          4
        ],
        [
          "월드컵",
          3
        ],
        [
          "바로가기",
          3
        ],
        [
          "프랑스",
          3
        ],
        [
          "감독",
          2
        ],
        [
          "안내",
          2
        ],
        [
          "공지",
          2
        ],
        [
          "프랑스는",
          2
        ],
        [
          "음바페",
          2
        ],
        [
          "토로한",
          1
        ],
        [
          "코치",
          1
        ],
        [
          "개선",
          1
        ],
        [
          "처우",
          1
        ],
        [
          "임창용이",
          1
        ],
        [
          "연봉",
          1
        ],
        [
          "시급",
          1
        ],
        [
          "레전드들이",
          1
        ],
        [
          "월급은",
          1
        ],
        [
          "개월만",
          1
        ],
        [
          "현장에",
          1
        ]
      ],
      "name_freq": [
        [
          "프랑스",
          7
        ],
        [
          "월드컵",
          5
        ],
        [
          "승부예",
          4
        ],
        [
          "바로가",
          3
        ],
        [
          "올리세",
          3
        ],
        [
          "음바페",
          3
        ],
        [
          "홍명보",
          2
        ],
        [
          "감독",
          2
        ],
        [
          "세요",
          2
        ],
        [
          "안내",
          2
        ],
        [
          "공지",
          2
        ],
        [
          "부아르",
          2
        ],
        [
          "코트디",
          2
        ]
      ],
      "angle_scores": [
        [
          "스포츠",
          6
        ]
      ]
    }
  },
  "topics": [
    {
      "title": "\"홍명보, 역대급 기록?\" 스포츠 레전드 기록 TOP10",
      "angle_type": "스포츠",
      "article_count": 6,
      "source_article": "\"코치 연봉 5천, 월급은 10개월만\"…임창용이 토로한, 레전드들이 현장에 없는 이유 \"처우 개선 시급\"",
      "source_url": "",
      "source_name": "스포츠 많이 본 뉴스",
      "related_names": [
        "홍명보",
        "감독",
        "코치",
        "연봉",
        "월급은"
      ],
      "template": "스포츠 기록",
      "score": 7.3,
      "dup_check": {
        "is_duplicate": false,
        "status": "통과",
        "matched_title": "",
        "matched_views": 0,
        "reason": ""
      },
      "table": {
        "headers": [
          "선수",
          "소속팀",
          "기록 내용",
          "기록 가치"
        ]
      },
      "channel": "초구딱"
    },
    {
      "title": "\"월드컵\" 관련 화제 스타 TOP10",
      "angle_type": "👤 월드컵",
      "article_count": 5,
      "source_article": "“홍명보 감독 월드컵 성공했어도 사퇴 고려”…12년 전 상처 더 벌어졌다, 끝내 자진해서 아웃",
      "source_url": "",
      "source_name": "스포츠 많이 본 뉴스",
      "related_names": [
        "월드컵"
      ],
      "template": "인맥",
      "score": 7.0,
      "dup_check": {
        "is_duplicate": false,
        "status": "통과",
        "matched_title": "",
        "matched_views": 0,
        "reason": ""
      },
      "table": {
        "headers": [
          "이름",
          "분류",
          "이슈 내용",
          "현재 상황"
        ]
      },
      "channel": "초구딱"
    },
    {
      "title": "\"프랑스\" 관련 화제 스타 TOP10",
      "angle_type": "👤 프랑스",
      "article_count": 7,
      "source_article": "프랑스는 체급이 다르네요",
      "source_url": "https://mlbpark.donga.com/mp/b.php?id=202607010116835617&p=1&b=bullpen&m=view&select=&query=&subselect=&subquery=&user=&site=donga.com",
      "source_name": "MLB파크 불펜",
      "related_names": [
        "프랑스"
      ],
      "template": "인맥",
      "score": 6.5,
      "dup_check": {
        "is_duplicate": false,
        "status": "통과",
        "matched_title": "",
        "matched_views": 0,
        "reason": ""
      },
      "table": {
        "headers": [
          "이름",
          "분류",
          "이슈 내용",
          "현재 상황"
        ]
      },
      "channel": "초구딱"
    },
    {
      "title": "\"승부예\" 관련 화제 스타 TOP10",
      "angle_type": "👤 승부예",
      "article_count": 4,
      "source_article": "🏆[6/30 Update!] 2026 북중미월드컵 승부예측 이벤트🏆",
      "source_url": "https://mlbpark.donga.com/mp/b.php?p=1&b=worldcup&id=202606100116098223",
      "source_name": "MLB파크 불펜",
      "related_names": [
        "승부예"
      ],
      "template": "인맥",
      "score": 6.5,
      "dup_check": {
        "is_duplicate": false,
        "status": "통과",
        "matched_title": "",
        "matched_views": 0,
        "reason": ""
      },
      "table": {
        "headers": [
          "이름",
          "분류",
          "이슈 내용",
          "현재 상황"
        ]
      },
      "channel": "초구딱"
    },
    {
      "title": "\"바로가\" 관련 화제 스타 TOP10",
      "angle_type": "👤 바로가",
      "article_count": 3,
      "source_article": "🏆7/1(수) 2026 WC 승부예측 바로가기 [32강]🏆",
      "source_url": "https://mlbpark.donga.com/mp/b.php?p=1&b=worldcup&id=202606290116776598",
      "source_name": "MLB파크 불펜",
      "related_names": [
        "바로가"
      ],
      "template": "인맥",
      "score": 6.0,
      "dup_check": {
        "is_duplicate": false,
        "status": "통과",
        "matched_title": "",
        "matched_views": 0,
        "reason": ""
      },
      "table": {
        "headers": [
          "이름",
          "분류",
          "이슈 내용",
          "현재 상황"
        ]
      },
      "channel": "초구딱"
    },
    {
      "title": "\"올리세\" 관련 화제 스타 TOP10",
      "angle_type": "👤 올리세",
      "article_count": 3,
      "source_article": "올리세 진짜 겁나게 잘하네요 ㄷㄷㄷㄷ",
      "source_url": "https://mlbpark.donga.com/mp/b.php?id=202607010116835611&p=1&b=bullpen&m=view&select=&query=&subselect=&subquery=&user=&site=donga.com",
      "source_name": "MLB파크 불펜",
      "related_names": [
        "올리세"
      ],
      "template": "인맥",
      "score": 6.0,
      "dup_check": {
        "is_duplicate": false,
        "status": "통과",
        "matched_title": "",
        "matched_views": 0,
        "reason": ""
      },
      "table": {
        "headers": [
          "이름",
          "분류",
          "이슈 내용",
          "현재 상황"
        ]
      },
      "channel": "초구딱"
    },
    {
      "title": "\"음바페\" 관련 화제 스타 TOP10",
      "angle_type": "👤 음바페",
      "article_count": 3,
      "source_article": "어제 비닐신.오늘 음바페",
      "source_url": "https://mlbpark.donga.com/mp/b.php?id=202607010116835563&p=1&b=bullpen&m=view&select=&query=&subselect=&subquery=&user=&site=donga.com",
      "source_name": "MLB파크 불펜",
      "related_names": [
        "음바페"
      ],
      "template": "인맥",
      "score": 6.0,
      "dup_check": {
        "is_duplicate": false,
        "status": "통과",
        "matched_title": "",
        "matched_views": 0,
        "reason": ""
      },
      "table": {
        "headers": [
          "이름",
          "분류",
          "이슈 내용",
          "현재 상황"
        ]
      },
      "channel": "초구딱"
    }
  ],
  "all_topics": [
    {
      "title": "\"월드컵\" 관련 화제 스타 TOP10",
      "angle_type": "👤 월드컵",
      "article_count": 6,
      "source_article": "어디 홍명보가 끝일쏘냐!..\"2030년 월드컵, 정중히 부탁\" 손흥민 사과에 김희철 등 ★들 들썩",
      "source_url": "https://m.entertain.naver.com/article/108/0003448771",
      "source_name": "엔터 많이 본 뉴스",
      "related_names": [
        "월드컵"
      ],
      "template": "인맥",
      "score": 7.4,
      "dup_check": {
        "is_duplicate": false,
        "status": "통과",
        "matched_title": "",
        "matched_views": 0,
        "reason": ""
      },
      "table": {
        "headers": [
          "이름",
          "분류",
          "이슈 내용",
          "현재 상황"
        ]
      },
      "channel": "정보주는하마"
    },
    {
      "title": "\"이 둘이 가족이라고?\" 놀라운 연예계 혈연 TOP10",
      "angle_type": "가족·혈연",
      "article_count": 3,
      "source_article": "\"5분 대기조처럼...\" 이혼 최동석, 손주 시중드는 부모님 보며 '씁쓸·뭉클'",
      "source_url": "https://m.entertain.naver.com/article/076/0004420761",
      "source_name": "엔터 많이 본 뉴스",
      "related_names": [
        "대기조",
        "이혼",
        "최동석",
        "손주",
        "시중드"
      ],
      "template": "동갑내기",
      "score": 6.9,
      "dup_check": {
        "is_duplicate": false,
        "status": "통과",
        "matched_title": "",
        "matched_views": 0,
        "reason": ""
      },
      "table": {
        "headers": [
          "이름",
          "나이",
          "대표작",
          "현재 활동"
        ]
      },
      "channel": "정보주는하마"
    },
    {
      "title": "\"임신 결혼 상대가 누구?\" 화제의 결혼 발표 스타 TOP10",
      "angle_type": "결혼·이혼",
      "article_count": 9,
      "source_article": "배우♥아나운서 부부 탄생...'혼전 임신' 발표→\"새로운 생명 찾아왔다\"",
      "source_url": "https://m.entertain.naver.com/article/445/0000432524",
      "source_name": "엔터 많이 본 뉴스",
      "related_names": [
        "임신",
        "결혼",
        "부부",
        "생명",
        "열애"
      ],
      "template": "결혼 화제",
      "score": 6.8,
      "dup_check": {
        "is_duplicate": false,
        "status": "통과",
        "matched_title": "",
        "matched_views": 0,
        "reason": ""
      },
      "table": {
        "headers": [
          "이름",
          "배우자",
          "결혼 시점",
          "화제 포인트"
        ]
      },
      "channel": "정보주는하마"
    },
    {
      "title": "\"홍명보, 역대급 기록?\" 스포츠 레전드 기록 TOP10",
      "angle_type": "스포츠",
      "article_count": 4,
      "source_article": "“이재명 대통령이 문체부에 조사 지시하자, 홍명보 감독이 즉각 사임해” 글로벌 스포츠 전문 매체 디 애슬레틱, 韓 축구 집중 조명",
      "source_url": "",
      "source_name": "스포츠 많이 본 뉴스",
      "related_names": [
        "홍명보",
        "이재명",
        "문체부",
        "조사",
        "지시하"
      ],
      "template": "스포츠 기록",
      "score": 6.8,
      "dup_check": {
        "is_duplicate": false,
        "status": "통과",
        "matched_title": "",
        "matched_views": 0,
        "reason": ""
      },
      "table": {
        "headers": [
          "선수",
          "소속팀",
          "기록 내용",
          "기록 가치"
        ]
      },
      "channel": "정보주는하마"
    },
    {
      "title": "\"배재고까지 이럴 줄은...\" 올해 팬들 분노 터진 스타 TOP10",
      "angle_type": "논란·사건",
      "article_count": 3,
      "source_article": "JK김동욱, ‘5·18 조롱구호 논란’ 배재고 교육청 조사에 “제대로 긁혔구나”",
      "source_url": "https://m.entertain.naver.com/article/144/0001123554",
      "source_name": "엔터 많이 본 뉴스",
      "related_names": [
        "배재고",
        "스타벅",
        "가야지",
        "김동욱",
        "조롱구"
      ],
      "template": "논란 집합",
      "score": 6.5,
      "dup_check": {
        "is_duplicate": false,
        "status": "통과",
        "matched_title": "",
        "matched_views": 0,
        "reason": ""
      },
      "table": {
        "headers": [
          "이름",
          "소속·직업",
          "논란 내용",
          "현재 상황"
        ]
      },
      "channel": "정보주는하마"
    },
    {
      "title": "\"축구\" 관련 화제 스타 TOP10",
      "angle_type": "👤 축구",
      "article_count": 4,
      "source_article": "홍명보 사퇴하고 6시간 뒤…'한국행 결렬' 마치는 캐나다 축구 영웅 됐다→\"역사적인 질주\" 英 BBC 등 외신도 극찬",
      "source_url": "",
      "source_name": "스포츠 많이 본 뉴스",
      "related_names": [
        "축구"
      ],
      "template": "인맥",
      "score": 6.5,
      "dup_check": {
        "is_duplicate": false,
        "status": "재활용 가능",
        "matched_title": "\"임영웅, 손흥민이랑 조기축구?\" 축구 좀 찬다고 알려진 스타 TOP10 #연예인 #스포츠 #축구",
        "matched_views": 32359,
        "reason": "기간 경과 104일"
      },
      "table": {
        "headers": [
          "이름",
          "분류",
          "이슈 내용",
          "현재 상황"
        ]
      },
      "channel": "정보주는하마"
    },
    {
      "title": "\"극찬\" 관련 화제 스타 TOP10",
      "angle_type": "👤 극찬",
      "article_count": 3,
      "source_article": "성시경, 문가영 극찬…\"너무 예쁘고 고급스러워\"",
      "source_url": "https://m.entertain.naver.com/article/003/0014035457",
      "source_name": "엔터 많이 본 뉴스",
      "related_names": [
        "극찬"
      ],
      "template": "인맥",
      "score": 6.0,
      "dup_check": {
        "is_duplicate": false,
        "status": "통과",
        "matched_title": "",
        "matched_views": 0,
        "reason": ""
      },
      "table": {
        "headers": [
          "이름",
          "분류",
          "이슈 내용",
          "현재 상황"
        ]
      },
      "channel": "정보주는하마"
    },
    {
      "title": "\"매체\" 관련 화제 스타 TOP10",
      "angle_type": "👤 매체",
      "article_count": 3,
      "source_article": "'벤투, 흥미로운 제안 기다리고 있다'…공백기 조명한 포르투갈 매체→韓 팬들은 '제발 돌아와 주세요'",
      "source_url": "",
      "source_name": "스포츠 많이 본 뉴스",
      "related_names": [
        "매체"
      ],
      "template": "인맥",
      "score": 6.0,
      "dup_check": {
        "is_duplicate": false,
        "status": "통과",
        "matched_title": "",
        "matched_views": 0,
        "reason": ""
      },
      "table": {
        "headers": [
          "이름",
          "분류",
          "이슈 내용",
          "현재 상황"
        ]
      },
      "channel": "정보주는하마"
    },
    {
      "title": "\"그때 그 사람, 지금은?\" 근황 궁금한 스타 TOP10",
      "angle_type": "복귀·근황",
      "article_count": 2,
      "source_article": "'벤투, 흥미로운 제안 기다리고 있다'…공백기 조명한 포르투갈 매체→韓 팬들은 '제발 돌아와 주세요'",
      "source_url": "",
      "source_name": "스포츠 많이 본 뉴스",
      "related_names": [
        "스타강",
        "김미경",
        "빼고",
        "얼굴",
        "몰라볼"
      ],
      "template": "장기 공백 복귀",
      "score": 5.8,
      "dup_check": {
        "is_duplicate": false,
        "status": "통과",
        "matched_title": "",
        "matched_views": 0,
        "reason": ""
      },
      "table": {
        "headers": [
          "이름",
          "공백 기간",
          "공백 사유",
          "복귀 작품"
        ]
      },
      "channel": "정보주는하마"
    },
    {
      "title": "\"죽을 고비 넘기고 돌아왔다\" 투병 이겨낸 스타 TOP10",
      "angle_type": "투병·건강",
      "article_count": 2,
      "source_article": "\"사망 이틀 전 찜질방 같이 갔는데\" 故 강수연, 향년 56세→동료 여배우 '그리움' 호소 ('당신이아픈사이')",
      "source_url": "https://m.entertain.naver.com/article/445/0000432558",
      "source_name": "엔터 많이 본 뉴스",
      "related_names": [
        "사망",
        "이틀",
        "찜질방",
        "같이",
        "갔는데"
      ],
      "template": "투병 극복",
      "score": 5.5,
      "dup_check": {
        "is_duplicate": false,
        "status": "통과",
        "matched_title": "",
        "matched_views": 0,
        "reason": ""
      },
      "table": {
        "headers": [
          "이름",
          "투병 질환",
          "공백기",
          "복귀 작품"
        ]
      },
      "channel": "정보주는하마"
    },
    {
      "title": "\"홍명보, 역대급 기록?\" 스포츠 레전드 기록 TOP10",
      "angle_type": "스포츠",
      "article_count": 6,
      "source_article": "\"코치 연봉 5천, 월급은 10개월만\"…임창용이 토로한, 레전드들이 현장에 없는 이유 \"처우 개선 시급\"",
      "source_url": "",
      "source_name": "스포츠 많이 본 뉴스",
      "related_names": [
        "홍명보",
        "감독",
        "코치",
        "연봉",
        "월급은"
      ],
      "template": "스포츠 기록",
      "score": 7.3,
      "dup_check": {
        "is_duplicate": false,
        "status": "통과",
        "matched_title": "",
        "matched_views": 0,
        "reason": ""
      },
      "table": {
        "headers": [
          "선수",
          "소속팀",
          "기록 내용",
          "기록 가치"
        ]
      },
      "channel": "초구딱"
    },
    {
      "title": "\"월드컵\" 관련 화제 스타 TOP10",
      "angle_type": "👤 월드컵",
      "article_count": 5,
      "source_article": "“홍명보 감독 월드컵 성공했어도 사퇴 고려”…12년 전 상처 더 벌어졌다, 끝내 자진해서 아웃",
      "source_url": "",
      "source_name": "스포츠 많이 본 뉴스",
      "related_names": [
        "월드컵"
      ],
      "template": "인맥",
      "score": 7.0,
      "dup_check": {
        "is_duplicate": false,
        "status": "통과",
        "matched_title": "",
        "matched_views": 0,
        "reason": ""
      },
      "table": {
        "headers": [
          "이름",
          "분류",
          "이슈 내용",
          "현재 상황"
        ]
      },
      "channel": "초구딱"
    },
    {
      "title": "\"프랑스\" 관련 화제 스타 TOP10",
      "angle_type": "👤 프랑스",
      "article_count": 7,
      "source_article": "프랑스는 체급이 다르네요",
      "source_url": "https://mlbpark.donga.com/mp/b.php?id=202607010116835617&p=1&b=bullpen&m=view&select=&query=&subselect=&subquery=&user=&site=donga.com",
      "source_name": "MLB파크 불펜",
      "related_names": [
        "프랑스"
      ],
      "template": "인맥",
      "score": 6.5,
      "dup_check": {
        "is_duplicate": false,
        "status": "통과",
        "matched_title": "",
        "matched_views": 0,
        "reason": ""
      },
      "table": {
        "headers": [
          "이름",
          "분류",
          "이슈 내용",
          "현재 상황"
        ]
      },
      "channel": "초구딱"
    },
    {
      "title": "\"승부예\" 관련 화제 스타 TOP10",
      "angle_type": "👤 승부예",
      "article_count": 4,
      "source_article": "🏆[6/30 Update!] 2026 북중미월드컵 승부예측 이벤트🏆",
      "source_url": "https://mlbpark.donga.com/mp/b.php?p=1&b=worldcup&id=202606100116098223",
      "source_name": "MLB파크 불펜",
      "related_names": [
        "승부예"
      ],
      "template": "인맥",
      "score": 6.5,
      "dup_check": {
        "is_duplicate": false,
        "status": "통과",
        "matched_title": "",
        "matched_views": 0,
        "reason": ""
      },
      "table": {
        "headers": [
          "이름",
          "분류",
          "이슈 내용",
          "현재 상황"
        ]
      },
      "channel": "초구딱"
    },
    {
      "title": "\"바로가\" 관련 화제 스타 TOP10",
      "angle_type": "👤 바로가",
      "article_count": 3,
      "source_article": "🏆7/1(수) 2026 WC 승부예측 바로가기 [32강]🏆",
      "source_url": "https://mlbpark.donga.com/mp/b.php?p=1&b=worldcup&id=202606290116776598",
      "source_name": "MLB파크 불펜",
      "related_names": [
        "바로가"
      ],
      "template": "인맥",
      "score": 6.0,
      "dup_check": {
        "is_duplicate": false,
        "status": "통과",
        "matched_title": "",
        "matched_views": 0,
        "reason": ""
      },
      "table": {
        "headers": [
          "이름",
          "분류",
          "이슈 내용",
          "현재 상황"
        ]
      },
      "channel": "초구딱"
    },
    {
      "title": "\"올리세\" 관련 화제 스타 TOP10",
      "angle_type": "👤 올리세",
      "article_count": 3,
      "source_article": "올리세 진짜 겁나게 잘하네요 ㄷㄷㄷㄷ",
      "source_url": "https://mlbpark.donga.com/mp/b.php?id=202607010116835611&p=1&b=bullpen&m=view&select=&query=&subselect=&subquery=&user=&site=donga.com",
      "source_name": "MLB파크 불펜",
      "related_names": [
        "올리세"
      ],
      "template": "인맥",
      "score": 6.0,
      "dup_check": {
        "is_duplicate": false,
        "status": "통과",
        "matched_title": "",
        "matched_views": 0,
        "reason": ""
      },
      "table": {
        "headers": [
          "이름",
          "분류",
          "이슈 내용",
          "현재 상황"
        ]
      },
      "channel": "초구딱"
    },
    {
      "title": "\"음바페\" 관련 화제 스타 TOP10",
      "angle_type": "👤 음바페",
      "article_count": 3,
      "source_article": "어제 비닐신.오늘 음바페",
      "source_url": "https://mlbpark.donga.com/mp/b.php?id=202607010116835563&p=1&b=bullpen&m=view&select=&query=&subselect=&subquery=&user=&site=donga.com",
      "source_name": "MLB파크 불펜",
      "related_names": [
        "음바페"
      ],
      "template": "인맥",
      "score": 6.0,
      "dup_check": {
        "is_duplicate": false,
        "status": "통과",
        "matched_title": "",
        "matched_views": 0,
        "reason": ""
      },
      "table": {
        "headers": [
          "이름",
          "분류",
          "이슈 내용",
          "현재 상황"
        ]
      },
      "channel": "초구딱"
    }
  ],
  "keyword_freq": [
    [
      "월드컵",
      4
    ],
    [
      "배재고",
      4
    ],
    [
      "축구",
      4
    ],
    [
      "임신",
      3
    ],
    [
      "결혼",
      3
    ],
    [
      "극찬",
      3
    ],
    [
      "홍명보",
      3
    ],
    [
      "매체",
      3
    ],
    [
      "부부",
      2
    ],
    [
      "생명",
      2
    ],
    [
      "인정",
      2
    ],
    [
      "열애",
      2
    ],
    [
      "사망",
      2
    ],
    [
      "내가",
      2
    ],
    [
      "깜짝",
      2
    ],
    [
      "이제",
      2
    ],
    [
      "얼굴",
      2
    ],
    [
      "불꽃야구",
      2
    ],
    [
      "위로",
      2
    ],
    [
      "가야지",
      2
    ]
  ],
  "name_freq": [
    [
      "홍명보",
      6
    ],
    [
      "월드컵",
      6
    ],
    [
      "배재고",
      4
    ],
    [
      "축구",
      4
    ],
    [
      "임신",
      3
    ],
    [
      "결혼",
      3
    ],
    [
      "극찬",
      3
    ],
    [
      "매체",
      3
    ],
    [
      "생명",
      2
    ],
    [
      "부부",
      2
    ],
    [
      "인정",
      2
    ],
    [
      "열애",
      2
    ],
    [
      "사망",
      2
    ],
    [
      "내가",
      2
    ],
    [
      "깜짝",
      2
    ]
  ],
  "total_topics_generated": 17,
  "valid_topics": 17,
  "excluded_duplicates": 0
}